ODEpower/ODEgraph.py
ODEpower/ODEmatlab.py
ODEpower/ODEplot.py
ODEpower/ODEpower.py
ODEpower/ODEsimulation.py
ODEpower/ODEtool.py
ODEpower/__init__.py
ODEpower/components_connection.py
ODEpower/components_control.py
ODEpower/components_electric.py
ODEpower/config.py
ODEpower/prettyPlot.py
odepower-0.9.1.dist-info/licenses/LICENSE.txt
odepower-0.9.1.dist-info/METADATA
odepower-0.9.1.dist-info/WHEEL
odepower-0.9.1.dist-info/top_level.txt
odepower-0.9.1.dist-info/RECORD
