Metadata-Version: 2.4
Name: ODEpower
Version: 0.9.1
Summary: ODE-based power system modeling and simulation package
Author-email: Robert Annuth <robert.annuth@tuhh.de>
License-Expression: GPL-3.0-only
Project-URL: Homepage, https://github.com/rAnnuth/ODEpower
Requires-Python: >=3.7
License-File: LICENSE.txt
Requires-Dist: scipy
Requires-Dist: sympy
Requires-Dist: pandas
Requires-Dist: numpy
Requires-Dist: control
Requires-Dist: tabulate
Requires-Dist: networkx
Requires-Dist: matlabengine==24.2.2
Dynamic: license-file
